main.py
archive_cli-0.1.0.dist-info/METADATA
archive_cli-0.1.0.dist-info/WHEEL
archive_cli-0.1.0.dist-info/top_level.txt
archive_cli-0.1.0.dist-info/RECORD
