Metadata-Version: 2.4
Name: archive-cli
Version: 0.1.0
Summary: Add your description here
Requires-Python: >=3.13
Requires-Dist: prompt-toolkit>=3.0.52
Requires-Dist: typer>=0.17.4
